{
 "alias": "Leblanc",
 "id": 7,
 "name": "ルブラン",
 "title": "幻惑の奇術師",
 "patch": "16.13.7915903+branch.releases-16-13.content.release",
 "skills": {
  "passive": {
   "name": "鏡像",
   "description": "自身の体力が40%を下回ると、1秒間<keywordStealth>インビジブル</keywordStealth>状態になり、ダメージを与えない分身を8秒間発生させる。分身はAltキーで動かせる。<br><br><rules><keywordStealth>インビジブル</keywordStealth>状態のユニットは、タワーまたは<font color='#ee91d7'>真の視界</font color>によってのみ可視化される。</rules>",
   "source": "stringtable",
   "unresolved": []
  },
  "q": {
   "name": "シジルマリス",
   "description": "敵1体に刻印を飛ばし、<magicDamage>65/90/115/140/165（＋魔力の40%）の魔法ダメージ</magicDamage>を与えて、3.5秒間マークする。<br><br>マークした対象にスキルでダメージを与えると、刻印が爆発して<magicDamage>65/90/115/140/165（＋魔力の40%）の魔法ダメージ</magicDamage>を与える。<br><br>どちらかのダメージで対象をキルした場合、マナコストの100%が回復し、このスキルの残りクールダウンが30%解消される。<br><br><rules>最初の刻印はミニオンに対して10〜146（レベル1〜18）の追加ダメージを与える。</rules>",
   "cooldown": "6",
   "cost": "50",
   "range": "700",
   "maxRank": 5,
   "unresolved": []
  },
  "w": {
   "name": "ディストーション",
   "description": "ダッシュし、周囲の敵に<magicDamage>75/115/155/195/235（＋魔力の80%）の魔法ダメージ</magicDamage>を与える。ダッシュ後の4秒間、このスキルを<recast>再発動</recast>できる。<br><br><recast>再発動:</recast> ルブランが元の場所に戻る。",
   "cooldown": "15/13.75/12.5/11.25/10",
   "cost": "60/70/80/90/100",
   "range": "600",
   "maxRank": 5,
   "unresolved": []
  },
  "e": {
   "name": "エーテルチェイン",
   "description": "鎖を放ち、最初に命中した敵に<magicDamage>50/70/90/110/130（＋魔力の40%）の魔法ダメージ</magicDamage>を与えて鎖に繋ぎ、<keywordStealth>真の視界</keywordStealth>を付与する。<br><br>対象が1.5秒間鎖に繋がれたままの場合、対象に1.5秒間の<status>スネア効果</status>を与え、追加で<magicDamage>80/120/160/200/240（＋魔力の85%）の魔法ダメージ</magicDamage>を与える。",
   "cooldown": "14/13.25/12.5/11.75/11",
   "cost": "50",
   "range": "925",
   "maxRank": 5,
   "unresolved": []
  },
  "r": {
   "name": "再演",
   "description": "直前に使用したスキルを再演(コピーして再使用)する。再演したスキルはダメージが増加する。<br><br><spellName>「再演: シジルマリス」</spellName>は刻印の適用時に<magicDamage>70/150/230（＋魔力の40%）の魔法ダメージ</magicDamage>を与え、消費時に<magicDamage>140/300/460（＋魔力の80%）の魔法ダメージ</magicDamage>を与える。<br><spellName>「再演: ディストーション」</spellName>は<magicDamage>150/315/480（＋魔力の80%）の魔法ダメージ</magicDamage>を与える。<br><spellName>「再演: エーテルチェイン」</spellName>は鎖で繋いだ際に<magicDamage>70/150/230（＋魔力の40%）の魔法ダメージ</magicDamage>を与え、<status>スネア効果</status>付与時に<magicDamage>140/300/460（＋魔力の85%）の魔法ダメージ</magicDamage>を与える。",
   "cooldown": "45/35/25",
   "cost": "",
   "range": "25000",
   "maxRank": 3,
   "unresolved": []
  }
 },
 "unresolvedCount": 0
}